oc_checksumsworker_mongo/__init__.py
oc_checksumsworker_mongo/__main__.py
oc_checksumsworker_mongo/checksums_worker_mongo.py
oc_checksumsworker_mongo/mongo_api_client.py
oc_checksumsworker_mongo-0.1.2.dist-info/LICENSE
oc_checksumsworker_mongo-0.1.2.dist-info/METADATA
oc_checksumsworker_mongo-0.1.2.dist-info/WHEEL
oc_checksumsworker_mongo-0.1.2.dist-info/top_level.txt
oc_checksumsworker_mongo-0.1.2.dist-info/RECORD
